MANIFEST.in
README.rst
setup.cfg
setup.py
Products/__init__.py
Products.CMFPlomino.egg-info/PKG-INFO
Products.CMFPlomino.egg-info/SOURCES.txt
Products.CMFPlomino.egg-info/dependency_links.txt
Products.CMFPlomino.egg-info/entry_points.txt
Products.CMFPlomino.egg-info/namespace_packages.txt
Products.CMFPlomino.egg-info/not-zip-safe
Products.CMFPlomino.egg-info/requires.txt
Products.CMFPlomino.egg-info/top_level.txt
Products/CMFPlomino/AppConfig.py
Products/CMFPlomino/HttpUtils.py
Products/CMFPlomino/PlominoAccessControl.py
Products/CMFPlomino/PlominoAction.py
Products/CMFPlomino/PlominoAgent.py
Products/CMFPlomino/PlominoCache.py
Products/CMFPlomino/PlominoColumn.py
Products/CMFPlomino/PlominoDatabase.py
Products/CMFPlomino/PlominoDesignManager.py
Products/CMFPlomino/PlominoDocument.py
Products/CMFPlomino/PlominoField.py
Products/CMFPlomino/PlominoForm.py
Products/CMFPlomino/PlominoHidewhen.py
Products/CMFPlomino/PlominoReplicationManager.py
Products/CMFPlomino/PlominoUtils.py
Products/CMFPlomino/PlominoView.py
Products/CMFPlomino/__init__.py
Products/CMFPlomino/config.py
Products/CMFPlomino/configure.zcml
Products/CMFPlomino/events.py
Products/CMFPlomino/exceptions.py
Products/CMFPlomino/install.txt
Products/CMFPlomino/interfaces.py
Products/CMFPlomino/profiles.zcml
Products/CMFPlomino/setuphandlers.py
Products/CMFPlomino/testing.py
Products/CMFPlomino/upgrades.py
Products/CMFPlomino/upgrades.zcml
Products/CMFPlomino/validator.py
Products/CMFPlomino/version.txt
Products/CMFPlomino/browser/__init__.py
Products/CMFPlomino/browser/configure.zcml
Products/CMFPlomino/browser/design_portlet.pt
Products/CMFPlomino/browser/element_portlet.pt
Products/CMFPlomino/browser/portlet.py
Products/CMFPlomino/browser/javascript/__init__.py
Products/CMFPlomino/browser/javascript/jquery.json-2.2.min.js
Products/CMFPlomino/browser/javascript/jquery.urlEncode.js
Products/CMFPlomino/browser/javascript/plomino.accordion.js
Products/CMFPlomino/browser/javascript/plomino.codemirror.js
Products/CMFPlomino/browser/javascript/plomino.datagrid.js
Products/CMFPlomino/browser/javascript/plomino.datepicker.js
Products/CMFPlomino/browser/javascript/plomino.debug.js
Products/CMFPlomino/browser/javascript/plomino.design.js
Products/CMFPlomino/browser/javascript/plomino.dynamicview.js
Products/CMFPlomino/fields/CUSTOMFIELD_HOWTO.txt
