Metadata-Version: 1.1
Name: Products.CMFPlomino
Version: 1.19.6
Summary: Create specific applications in Plone without developing. Created by Makina Corpus.
Home-page: http://www.plomino.net
Author: Eric BREHAULT
Author-email: eric.brehault@makina-corpus.org
License: ZPL
Keywords: RAD,dynamic forms,web application builder
Platform: UNKNOWN
Classifier: Framework :: Plone
Classifier: Programming Language :: Python
